{"251":{"issue":"[E251] Bluefox was not found in the collaborators on [NPM](https://www.npmjs.com/package/iobroker.energy-tracker)!. Please execute in adapter directory: `npm owner add bluefox iobroker.energy-tracker`","adapter":"energy-tracker/ioBroker.energy-tracker","timestamp":"Wed, 25 Jun 2025 06:47:15 GMT"},"401":{"issue":"[W401] Cannot find \"energy-tracker\" in latest repository","adapter":"energy-tracker/ioBroker.energy-tracker","timestamp":"Wed, 25 Jun 2025 06:47:15 GMT"},"019":{"issue":"[E019] Invalid repository URL in [package.json](https://github.com/energy-tracker/ioBroker.energy-tracker/blob/master/package.json): https://github.com/energy-tracker/iobroker.energy-tracker.git. Expected: git@github.com:energy-tracker/ioBroker.energy-tracker.git or https://github.com/energy-tracker/ioBroker.energy-tracker.git","adapter":"energy-tracker/ioBroker.energy-tracker","timestamp":"Wed, 25 Jun 2025 06:47:15 GMT"}}