{"156":{"issue":"[W156] admin 6.17.14 listed as dependency but 7.4.10 is recommended. Please consider updating globalDependency at [io-package.json](https://github.com/ronny130286/ioBroker.ankersolix2/blob/master/io-package.json).","adapter":"ronny130286/ioBroker.ankersolix2","timestamp":"Thu, 06 Mar 2025 19:48:03 GMT"},"195":{"issue":"[W195] Protected or encrypted element \"password\" should be listed at \"native\" in [io-package.json](https://github.com/ronny130286/ioBroker.ankersolix2/blob/master/io-package.json)","adapter":"ronny130286/ioBroker.ankersolix2","timestamp":"Thu, 06 Mar 2025 19:48:03 GMT"},"401":{"issue":"[W401] Cannot find \"ankersolix2\" in latest repository","adapter":"ronny130286/ioBroker.ankersolix2","timestamp":"Thu, 06 Mar 2025 19:48:03 GMT"}}