{"184":{"issue":"[W184] \"common.title\" is deprecated and replaced by \"common.titleLang\". Please remove from [io-package.json](https://github.com/ioBroker/ioBroker.hm-rpc/blob/master/io-package.json).","adapter":"ioBroker/ioBroker.hm-rpc","timestamp":"Fri, 18 Oct 2024 03:27:52 GMT"},"526":{"issue":"[S526] Consider adding plugin \"@alcalzone/release-script-plugin-manual-review\".","adapter":"ioBroker/ioBroker.hm-rpc","timestamp":"Fri, 18 Oct 2024 03:27:52 GMT"},"951":{"issue":"[W951] .npmignore found but \"files\" is used at [package.json](https://github.com/ioBroker/ioBroker.hm-rpc/blob/master/package.json). Please remove .npmignore.","adapter":"ioBroker/ioBroker.hm-rpc","timestamp":"Fri, 18 Oct 2024 03:27:52 GMT"}}