{"184":{"issue":"[W184] \"common.materialize\" is deprecated for admin >= 5 at [io-package.json](https://github.com/iobroker-community-adapters/ioBroker.mihome-vacuum/blob/master/io-package.json). Please use property \"adminUI\".","adapter":"iobroker-community-adapters/ioBroker.mihome-vacuum","timestamp":"Thu, 06 Feb 2025 22:11:39 GMT"},"513":{"issue":"[W513] \"gulpfile.js\" found in repo! Think about migrating to @iobroker/adapter-dev package","adapter":"iobroker-community-adapters/ioBroker.mihome-vacuum","timestamp":"Thu, 06 Feb 2025 22:11:39 GMT"},"522":{"issue":"[S522] Please consider migrating to admin 5 UI (jsonConfig).","adapter":"iobroker-community-adapters/ioBroker.mihome-vacuum","timestamp":"Thu, 06 Feb 2025 22:11:39 GMT"},"528":{"issue":"[E528] Plugin \"license\" missing at .releaseconfig.json. Please add.","adapter":"iobroker-community-adapters/ioBroker.mihome-vacuum","timestamp":"Thu, 06 Feb 2025 22:11:39 GMT"},"529":{"issue":"[W529] Plugin \"manual-review\" missing at .releaseconfig.json. Please add.","adapter":"iobroker-community-adapters/ioBroker.mihome-vacuum","timestamp":"Thu, 06 Feb 2025 22:11:39 GMT"},"804":{"issue":"[E804] Please process issue [[#992] \"Compatibility check and testing for Responsive Design (materialize)\"](https://github.com/iobroker-community-adapters/ioBroker.mihome-vacuum/issues/992)","adapter":"iobroker-community-adapters/ioBroker.mihome-vacuum","timestamp":"Thu, 06 Feb 2025 22:11:39 GMT"},"034":{"issue":"[W034] @iobroker/adapter-core 3.2.1 specified. 3.2.2 is recommended. Please consider updating dependencies at [package.json](https://github.com/iobroker-community-adapters/ioBroker.mihome-vacuum/blob/master/package.json)","adapter":"iobroker-community-adapters/ioBroker.mihome-vacuum","timestamp":"Thu, 06 Feb 2025 22:11:39 GMT"},"051":{"issue":"[W051] 'request' package is deprecated and no longer maintained. Please consider migrating to package 'axios'.","adapter":"iobroker-community-adapters/ioBroker.mihome-vacuum","timestamp":"Thu, 06 Feb 2025 22:11:39 GMT"}}