{"5032":{"issue":"[S5032] \"lib/tools.js\" found in repo but not used anywhere. Consider removing file.","adapter":"iobroker-community-adapters/ioBroker.gsmsms","timestamp":"Thu, 30 Apr 2026 22:15:39 GMT"},"5047":{"issue":"[W5047] \"admin/style.css\" is most likely outdated since jsonConfig is used. Please consider removing it.","adapter":"iobroker-community-adapters/ioBroker.gsmsms","timestamp":"Thu, 30 Apr 2026 22:15:39 GMT"},"8004":{"issue":"[W8004] Please process PR [[#145] \"[iobroker-bot] Drop Node.js 20 support (End of Life)\"](https://github.com/iobroker-community-adapters/ioBroker.gsmsms/issues/145)","adapter":"iobroker-community-adapters/ioBroker.gsmsms","timestamp":"Thu, 30 Apr 2026 22:15:39 GMT"},"8910":{"issue":"[S8910] File \"/.github/workflows/dependabot-auto-merge.yml.OLD\" was found. If it is no longer needed, consider deleting it.","adapter":"iobroker-community-adapters/ioBroker.gsmsms","timestamp":"Thu, 30 Apr 2026 22:15:39 GMT"}}