{"1056":{"issue":"[W1056] admin 7.6.17 listed as dependency but 7.6.20 is recommended. Please consider updating globalDependency at [io-package.json](https://github.com/iobroker-community-adapters/ioBroker.alias-manager/blob/master/io-package.json).","adapter":"iobroker-community-adapters/ioBroker.alias-manager","timestamp":"Thu, 23 Apr 2026 20:40:33 GMT"},"5022":{"issue":"[S5022] Please consider migrating to admin 5 UI (jsonConfig) or react based UI.","adapter":"iobroker-community-adapters/ioBroker.alias-manager","timestamp":"Thu, 23 Apr 2026 20:40:33 GMT"},"5041":{"issue":"[W5041] Example configuration (option1, option2) found in i18n translation files (en, de, ru, pt, nl, fr, it, es, pl, uk, zh-cn). Please remove example configuration from your code.","adapter":"iobroker-community-adapters/ioBroker.alias-manager","timestamp":"Thu, 23 Apr 2026 20:40:33 GMT"},"8004":{"issue":"[W8004] Please process PR [[#230] \"[iobroker-bot] Update Node.js versions in test-and-release workflow\"](https://github.com/iobroker-community-adapters/ioBroker.alias-manager/issues/230)","adapter":"iobroker-community-adapters/ioBroker.alias-manager","timestamp":"Thu, 23 Apr 2026 20:40:33 GMT"},"8910":{"issue":"[S8910] File \"/.github/workflows/dependabot-auto-merge.yml.OLD\" was found. If it is no longer needed, consider deleting it.","adapter":"iobroker-community-adapters/ioBroker.alias-manager","timestamp":"Thu, 23 Apr 2026 20:40:33 GMT"},"0050":{"issue":"[W0050] 'dependency @iobroker/adapter-core' seems to be obsolete as 'common.onlyWWW' is set to true.","adapter":"iobroker-community-adapters/ioBroker.alias-manager","timestamp":"Thu, 23 Apr 2026 20:40:33 GMT"}}