{"8004":{"issue":"[W8004] Please process PR [[#868] \"[iobroker-bot] Fix Schema Links for VSCode\"](https://github.com/hombach/ioBroker.kostal-piko-ba/issues/868)","adapter":"hombach/ioBroker.kostal-piko-ba","timestamp":"Tue, 23 Dec 2025 06:24:13 GMT"},"0063":{"issue":"[W0063] \"@types/sinon, sinon, @types/sinon-chai, sinon-chai\" are included by \"@iobroker/testing\". Remove from devDependencies at [package.json](https://github.com/hombach/ioBroker.kostal-piko-ba/blob/master/package.json)","adapter":"hombach/ioBroker.kostal-piko-ba","timestamp":"Tue, 23 Dec 2025 06:24:13 GMT"}}