{"103":{"issue":"[E103] \"common.name\" in [io-package.json](https://github.com/energy-tracker/ioBroker.energy-tracker/blob/master/io-package.json) must be equal to \"'\". Now is energy-tracker","adapter":"energy-tracker/ioBroker.energy-tracker","timestamp":"Tue, 24 Jun 2025 17:35:34 GMT"},"250":{"issue":"[E250] Not found on npm. Please publish","adapter":"energy-tracker/ioBroker.energy-tracker","timestamp":"Tue, 24 Jun 2025 17:35:34 GMT"},"401":{"issue":"[W401] Cannot find \"\" in latest repository","adapter":"energy-tracker/ioBroker.energy-tracker","timestamp":"Tue, 24 Jun 2025 17:35:34 GMT"},"606":{"issue":"[W606] Could not retrieve timestamp of LATEST revision at npm.","adapter":"energy-tracker/ioBroker.energy-tracker","timestamp":"Tue, 24 Jun 2025 17:35:34 GMT"},"003":{"issue":"[E003] Repository must have name ioBroker.adaptername, but now io\"b\"roker is in lowercase","adapter":"energy-tracker/ioBroker.energy-tracker","timestamp":"Tue, 24 Jun 2025 17:35:34 GMT"},"004":{"issue":"[E004] No adapter name found in URL: https://github.com/energy-tracker/iobroker.energy-tracker","adapter":"energy-tracker/ioBroker.energy-tracker","timestamp":"Tue, 24 Jun 2025 17:35:34 GMT"},"020":{"issue":"[E020] Name of adapter in [package.json](https://github.com/energy-tracker/ioBroker.energy-tracker/blob/master/package.json) must be lowercase and be equal to \"iobroker.\". Now is \"iobroker.energy-tracker\"","adapter":"energy-tracker/ioBroker.energy-tracker","timestamp":"Tue, 24 Jun 2025 17:35:34 GMT"}}