{"5042":{"issue":"[W5042] Package \"undici\" is used in source files but not found in dependencies of [package.json](https://github.com/iobroker-community-adapters/ioBroker.stiebel-isg/blob/master/package.json). Dependency might be missing.","adapter":"iobroker-community-adapters/ioBroker.stiebel-isg","timestamp":"Fri, 15 May 2026 01:31:18 GMT"},"8004":{"issue":"[W8004] Please process PR [[#179] \"[iobroker-bot] Setup Auto-Merge for ioBroker-Bot PRs\"](https://github.com/iobroker-community-adapters/ioBroker.stiebel-isg/issues/179)","adapter":"iobroker-community-adapters/ioBroker.stiebel-isg","timestamp":"Fri, 15 May 2026 01:31:18 GMT"}}