{"8004":{"issue":"[W8004] Please process PR [[#190] \"[iobroker-bot] Update Node.js versions in test-and-release workflow\"](https://github.com/rg-engineering/ioBroker.vis-2-widgets-weather-and-heating/issues/190)","adapter":"rg-engineering/ioBroker.vis-2-widgets-weather-and-heating","timestamp":"Wed, 11 Mar 2026 07:59:11 GMT"},"0037":{"issue":"[W0037] @alcalzone/release-script-plugin-manual-review 4.0.0 specified. 5.1.1 (or newer) is current. Please update devDependencies at [package.json](https://github.com/rg-engineering/ioBroker.vis-2-widgets-weather-and-heating/blob/master/package.json)","adapter":"rg-engineering/ioBroker.vis-2-widgets-weather-and-heating","timestamp":"Wed, 11 Mar 2026 07:59:11 GMT"}}